keystoneauthenticator/__init__.py
keystoneauthenticator/keystone.py
jupyterhub_keystoneauthenticator-0.2.6.dist-info/LICENSE
jupyterhub_keystoneauthenticator-0.2.6.dist-info/METADATA
jupyterhub_keystoneauthenticator-0.2.6.dist-info/WHEEL
jupyterhub_keystoneauthenticator-0.2.6.dist-info/entry_points.txt
jupyterhub_keystoneauthenticator-0.2.6.dist-info/top_level.txt
jupyterhub_keystoneauthenticator-0.2.6.dist-info/RECORD
