Metadata-Version: 2.1
Name: jupyterhub-keystoneauthenticator
Version: 0.2.6
Summary: Keystone Authenticator for JupyterHub
Home-page: https://github.com/chameleoncloud/keystoneauthenticator
Author: Jason Anderson
Author-email: jasonanderson@uchicago.edu
License: 3 Clause BSD
Platform: UNKNOWN
Requires-Dist: jupyterhub
Requires-Dist: keystoneauth1
Requires-Dist: tornado
Requires-Dist: traitlets
